ojuara.py
mth-1.0.dist-info/METADATA
mth-1.0.dist-info/WHEEL
mth-1.0.dist-info/top_level.txt
mth-1.0.dist-info/RECORD
