Metadata-Version: 2.1
Name: mth
Version: 1.0
Summary: Brincando com distribuição python
Home-page: UNKNOWN
Author: Ojuara Abaporujucaíba
Author-email: ojuara@araujo.com
License: UNKNOWN
Platform: UNKNOWN
